docker2ami
