Metadata-Version: 2.1
Name: mmuller88-docker-build-ami
Version: 0.7.6
Summary: Build Amazon EC2 AMI image using a Dockerfile
Home-page: https://github.com/mmuller88/docker-build-ami.git
Author: Michael Persson
Author-email: michael.ake.persson@gmail.com
License: Apache License, Version 2.0
Keywords: docker aws ami ec2
Platform: UNKNOWN
Classifier: Development Status :: 4 - Beta
Classifier: Environment :: Console
Classifier: Intended Audience :: System Administrators
Classifier: Intended Audience :: Developers
Classifier: License :: OSI Approved :: Apache Software License
Classifier: Operating System :: POSIX :: Linux
Classifier: Operating System :: MacOS :: MacOS X
Classifier: Programming Language :: Python
Requires-Python: >=2.7
Provides-Extra: test
